sicicalc/__init__.py
sicicalc-0.1.dist-info/METADATA
sicicalc-0.1.dist-info/WHEEL
sicicalc-0.1.dist-info/top_level.txt
sicicalc-0.1.dist-info/RECORD
