Metadata-Version: 2.1
Name: sicicalc
Version: 0.1
Summary: A Simple and Compound Intrest calculator
Home-page: UNKNOWN
Author: Snehashish Laskar
Author-email: snehashish.laskar@gmail.com
License: UNKNOWN
Platform: UNKNOWN
Classifier: Programming Language :: Python :: 3
Classifier: License :: OSI Approved :: MIT License
Classifier: Operating System :: OS Independent
